{
    "name": "Global Information",
    "numberOfRequests": {
        "total": 5000,
        "ok": 4667,
        "ko": 333
    },
    "minResponseTime": {
        "total": 29,
        "ok": 29,
        "ko": 60000
    },
    "maxResponseTime": {
        "total": 60015,
        "ok": 31160,
        "ko": 60015
    },
    "meanResponseTime": {
        "total": 4981,
        "ok": 1055,
        "ko": 60006
    },
    "standardDeviation": {
        "total": 15107,
        "ok": 3616,
        "ko": 3
    },
    "percentiles1": {
        "total": 49,
        "ok": 48,
        "ko": 60006
    },
    "percentiles2": {
        "total": 96,
        "ok": 79,
        "ko": 60008
    },
    "percentiles3": {
        "total": 60004,
        "ok": 7069,
        "ko": 60012
    },
    "percentiles4": {
        "total": 60009,
        "ok": 15095,
        "ko": 60014
    },
    "group1": {
        "name": "t < 800 ms",
        "count": 4065,
        "percentage": 81
    },
    "group2": {
        "name": "800 ms < t < 1200 ms",
        "count": 167,
        "percentage": 3
    },
    "group3": {
        "name": "t > 1200 ms",
        "count": 435,
        "percentage": 9
    },
    "group4": {
        "name": "failed",
        "count": 333,
        "percentage": 7
    },
    "meanNumberOfRequestsPerSecond": {
        "total": 18.273184102329832,
        "ok": 17.056190041114665,
        "ko": 1.2169940612151668
    }
}